gtdb_itol_decorate/__init__.py
gtdb_itol_decorate/__main__.py
gtdb_itol_decorate/decorate.py
gtdb_itol_decorate/gtdb.py
gtdb_itol_decorate/itol.py
gtdb_itol_decorate/newick.py
gtdb_itol_decorate/util.py
gtdb_itol_decorate-1.1.1.dist-info/LICENSE
gtdb_itol_decorate-1.1.1.dist-info/METADATA
gtdb_itol_decorate-1.1.1.dist-info/WHEEL
gtdb_itol_decorate-1.1.1.dist-info/entry_points.txt
gtdb_itol_decorate-1.1.1.dist-info/top_level.txt
gtdb_itol_decorate-1.1.1.dist-info/RECORD
